altspell_lytspel/__init__.py
altspell_lytspel/reverse.py
altspell_lytspel-0.3.0.dist-info/WHEEL
altspell_lytspel-0.3.0.dist-info/METADATA
altspell_lytspel-0.3.0.dist-info/RECORD
